README.rst
setup.py
rtsimple/__init__.py
rtsimple/alias.py
rtsimple/base.py
rtsimple/lists.py
rtsimple/movies.py
rtsimple.egg-info/PKG-INFO
rtsimple.egg-info/SOURCES.txt
rtsimple.egg-info/dependency_links.txt
rtsimple.egg-info/requires.txt
rtsimple.egg-info/top_level.txt