Metadata-Version: 1.1
Name: rtsimple
Version: 0.1.0
Summary: A Python wrapper for the Rotten Tomatoes API v1.0
Home-page: https://github.com/celiao/rtsimple
Author: Celia Oakley
Author-email: celia.oakley@alumni.stanford.edu
License: UNKNOWN
Download-URL: https://github.com/celiao/rtsimple/tarball/0.1.0
Keywords: movie,movies,rotten tomatoes,rotten,tomatoes,rt,wrapper,database,api
Platform: UNKNOWN
Classifier: Development Status :: 3 - Alpha
Classifier: Intended Audience :: Developers
Classifier: Operating System :: OS Independent
Classifier: Programming Language :: Python :: 2.7
Classifier: Programming Language :: Python :: 3
Classifier: Topic :: Utilities
